labtool/__init__.py
labtool/__main__.py
labtool/parse.py
labtool/encoders/__init__.py
labtool/encoders/csv.py
labtool/encoders/json.py
labtool/encoders/tab.py
labtool-0.0.34.dist-info/LICENSE
labtool-0.0.34.dist-info/METADATA
labtool-0.0.34.dist-info/WHEEL
labtool-0.0.34.dist-info/entry_points.txt
labtool-0.0.34.dist-info/top_level.txt
labtool-0.0.34.dist-info/RECORD
