Metadata-Version: 2.1
Name: labtool
Version: 0.0.34
Summary: A tool to analyze lab report files
Home-page: https://github.com/acpuchades/libtool
Author: Alejandro Caravaca Puchades
Author-email: acaravacapuchades+dev@gmail.com
License: UNKNOWN
Platform: UNKNOWN
Classifier: Programming Language :: Python :: 3
Classifier: Operating System :: OS Independent
Classifier: License :: OSI Approved :: GNU General Public License v3 (GPLv3)
Requires-Python: >=3.6
